datascale/__init__.py
datascale/datascale.py
datascale-1.1.1.dist-info/LICENSE.txt
datascale-1.1.1.dist-info/METADATA
datascale-1.1.1.dist-info/WHEEL
datascale-1.1.1.dist-info/top_level.txt
datascale-1.1.1.dist-info/RECORD
