Metadata-Version: 2.1
Name: datascale
Version: 1.1.1
Summary: Functions for automatic scaling of matplotlib plot axes/resolution to data
Home-page: https://github.com/benkrichman/datascale
Author: Benjamin Krichman
Author-email: benkrichman@gmail.com
License: MIT
Classifier: Programming Language :: Python :: 3
Classifier: License :: OSI Approved :: MIT License
Classifier: Intended Audience :: Science/Research
Classifier: Topic :: Scientific/Engineering
Classifier: Topic :: Scientific/Engineering :: Visualization
License-File: LICENSE.txt
Requires-Dist: matplotlib
